<?xml version="1.0" encoding="UTF-8"?>
<RequestPayload>
   <AppHdr>
      <Fr><FIId><FinInstnId><BICFI>STANKEKEXXX</BICFI></FinInstnId></FIId></Fr>
      <To><FIId><FinInstnId><BICFI>DBSSSGSGXXX</BICFI></FinInstnId></FIId></To>
      <BizMsgIdr>REF-78692</BizMsgIdr>
      <MsgDefIdr>pacs.009.001.08</MsgDefIdr>
      <CreDt>2025-02-17T14:38:23.228051</CreDt>
   </AppHdr>
   <Document>
      <FICdtTrf>
         <GrpHdr>
            <MsgId>REF-78692</MsgId>
            <CreDtTm>2025-02-17T14:38:23.228052</CreDtTm>
            <NbOfTxs>1</NbOfTxs>
         </GrpHdr>
         <CdtTrfTxInf>
            <IntrBkSttlmAmt Ccy="USD">459083.00</IntrBkSttlmAmt>
         </CdtTrfTxInf>
      </FICdtTrf>
   </Document>
</RequestPayload>