<?xml version="1.0" encoding="UTF-8"?>
<RequestPayload>
   <AppHdr>
      <Fr><FIId><FinInstnId><BICFI>HSBCHKHHXXX</BICFI></FinInstnId></FIId></Fr>
      <To><FIId><FinInstnId><BICFI>HSBCHKHHXXX</BICFI></FinInstnId></FIId></To>
      <BizMsgIdr>REF-35434</BizMsgIdr>
      <MsgDefIdr>pacs.009.001.08</MsgDefIdr>
      <CreDt>2025-02-17T14:38:23.593238</CreDt>
   </AppHdr>
   <Document>
      <FICdtTrf>
         <GrpHdr>
            <MsgId>REF-35434</MsgId>
            <CreDtTm>2025-02-17T14:38:23.593239</CreDtTm>
            <NbOfTxs>1</NbOfTxs>
         </GrpHdr>
         <CdtTrfTxInf>
            <IntrBkSttlmAmt Ccy="JPY">194292.00</IntrBkSttlmAmt>
         </CdtTrfTxInf>
      </FICdtTrf>
   </Document>
</RequestPayload>