<?xml version="1.0" encoding="UTF-8"?>
<RequestPayload>
   <AppHdr>
      <Fr><FIId><FinInstnId><BICFI>SCBLGB2LXXX</BICFI></FinInstnId></FIId></Fr>
      <To><FIId><FinInstnId><BICFI>DBSSSGSGXXX</BICFI></FinInstnId></FIId></To>
      <BizMsgIdr>REF-22955</BizMsgIdr>
      <MsgDefIdr>pacs.009.001.08</MsgDefIdr>
      <CreDt>2025-02-17T14:38:23.509898</CreDt>
   </AppHdr>
   <Document>
      <FICdtTrf>
         <GrpHdr>
            <MsgId>REF-22955</MsgId>
            <CreDtTm>2025-02-17T14:38:23.509899</CreDtTm>
            <NbOfTxs>1</NbOfTxs>
         </GrpHdr>
         <CdtTrfTxInf>
            <IntrBkSttlmAmt Ccy="CNY">234083.00</IntrBkSttlmAmt>
         </CdtTrfTxInf>
      </FICdtTrf>
   </Document>
</RequestPayload>