<?xml version="1.0" encoding="UTF-8"?>
<RequestPayload>
   <AppHdr>
      <Fr><FIId><FinInstnId><BICFI>OCBCSGSGXXX</BICFI></FinInstnId></FIId></Fr>
      <To><FIId><FinInstnId><BICFI>BNPPIT2LXXX</BICFI></FinInstnId></FIId></To>
      <BizMsgIdr>REF-23367</BizMsgIdr>
      <MsgDefIdr>pacs.009.001.08</MsgDefIdr>
      <CreDt>2025-02-17T14:38:23.413303</CreDt>
   </AppHdr>
   <Document>
      <FICdtTrf>
         <GrpHdr>
            <MsgId>REF-23367</MsgId>
            <CreDtTm>2025-02-17T14:38:23.413304</CreDtTm>
            <NbOfTxs>1</NbOfTxs>
         </GrpHdr>
         <CdtTrfTxInf>
            <IntrBkSttlmAmt Ccy="CNY">412986.00</IntrBkSttlmAmt>
         </CdtTrfTxInf>
      </FICdtTrf>
   </Document>
</RequestPayload>