<?xml version="1.0" encoding="UTF-8"?>
<RequestPayload>
   <AppHdr>
      <Fr><FIId><FinInstnId><BICFI>ICBKCNBJXXX</BICFI></FinInstnId></FIId></Fr>
      <To><FIId><FinInstnId><BICFI>OCBCSGSGXXX</BICFI></FinInstnId></FIId></To>
      <BizMsgIdr>REF-81263</BizMsgIdr>
      <MsgDefIdr>pacs.009.001.08</MsgDefIdr>
      <CreDt>2025-02-17T14:38:24.003108</CreDt>
   </AppHdr>
   <Document>
      <FICdtTrf>
         <GrpHdr>
            <MsgId>REF-81263</MsgId>
            <CreDtTm>2025-02-17T14:38:24.003109</CreDtTm>
            <NbOfTxs>1</NbOfTxs>
         </GrpHdr>
         <CdtTrfTxInf>
            <IntrBkSttlmAmt Ccy="SGD">29185.00</IntrBkSttlmAmt>
         </CdtTrfTxInf>
      </FICdtTrf>
   </Document>
</RequestPayload>