<?xml version="1.0" encoding="UTF-8"?>
<RequestPayload>
   <AppHdr>
      <Fr><FIId><FinInstnId><BICFI>BARCDEFFXXX</BICFI></FinInstnId></FIId></Fr>
      <To><FIId><FinInstnId><BICFI>DBSAZAJJXXX</BICFI></FinInstnId></FIId></To>
      <BizMsgIdr>REF-81487</BizMsgIdr>
      <MsgDefIdr>pacs.008.001.08</MsgDefIdr>
      <CreDt>2025-02-17T14:38:21.827335</CreDt>
   </AppHdr>
   <Document>
      <FIToFICstmrCdtTrf>
         <GrpHdr>
            <MsgId>REF-81487</MsgId>
            <CreDtTm>2025-02-17T14:38:21.827336</CreDtTm>
            <NbOfTxs>1</NbOfTxs>
         </GrpHdr>
         <CdtTrfTxInf>
            <IntrBkSttlmAmt Ccy="GBP">238351.00</IntrBkSttlmAmt>
            <Dbtr><Nm>Hayes and Sons</Nm></Dbtr>
            <Cdtr><Nm>Johnson Group</Nm></Cdtr>
         </CdtTrfTxInf>
      </FIToFICstmrCdtTrf>
   </Document>
</RequestPayload>