<?xml version="1.0" encoding="UTF-8"?>
<RequestPayload>
   <AppHdr>
      <Fr><FIId><FinInstnId><BICFI>HSBCHKHHXXX</BICFI></FinInstnId></FIId></Fr>
      <To><FIId><FinInstnId><BICFI>SOGEFRPPXXX</BICFI></FinInstnId></FIId></To>
      <BizMsgIdr>REF-97948</BizMsgIdr>
      <MsgDefIdr>pacs.008.001.08</MsgDefIdr>
      <CreDt>2025-02-17T14:38:21.641970</CreDt>
   </AppHdr>
   <Document>
      <FIToFICstmrCdtTrf>
         <GrpHdr>
            <MsgId>REF-97948</MsgId>
            <CreDtTm>2025-02-17T14:38:21.641971</CreDtTm>
            <NbOfTxs>1</NbOfTxs>
         </GrpHdr>
         <CdtTrfTxInf>
            <IntrBkSttlmAmt Ccy="XAU">1020510.00</IntrBkSttlmAmt>
            <Dbtr><Nm>Dean LLC</Nm></Dbtr>
            <Cdtr><Nm>Scott-Spencer</Nm></Cdtr>
         </CdtTrfTxInf>
      </FIToFICstmrCdtTrf>
   </Document>
</RequestPayload>