<?xml version="1.0" encoding="UTF-8"?>
<RequestPayload>
   <AppHdr>
      <Fr><FIId><FinInstnId><BICFI>RABONL2UXXX</BICFI></FinInstnId></FIId></Fr>
      <To><FIId><FinInstnId><BICFI>ZURICHZCHXXX</BICFI></FinInstnId></FIId></To>
      <BizMsgIdr>REF-92784</BizMsgIdr>
      <MsgDefIdr>pacs.008.001.08</MsgDefIdr>
      <CreDt>2025-02-17T14:38:23.184686</CreDt>
   </AppHdr>
   <Document>
      <FIToFICstmrCdtTrf>
         <GrpHdr>
            <MsgId>REF-92784</MsgId>
            <CreDtTm>2025-02-17T14:38:23.184687</CreDtTm>
            <NbOfTxs>1</NbOfTxs>
         </GrpHdr>
         <CdtTrfTxInf>
            <IntrBkSttlmAmt Ccy="XDR">290839.00</IntrBkSttlmAmt>
            <Dbtr><Nm>Rhodes-Fitzgerald</Nm></Dbtr>
            <Cdtr><Nm>Thompson PLC</Nm></Cdtr>
         </CdtTrfTxInf>
      </FIToFICstmrCdtTrf>
   </Document>
</RequestPayload>