<?xml version="1.0" encoding="UTF-8"?>
<RequestPayload>
   <AppHdr>
      <Fr><FIId><FinInstnId><BICFI>FBNINGLAXXX</BICFI></FinInstnId></FIId></Fr>
      <To><FIId><FinInstnId><BICFI>STANKEKEXXX</BICFI></FinInstnId></FIId></To>
      <BizMsgIdr>REF-37708</BizMsgIdr>
      <MsgDefIdr>pacs.008.001.08</MsgDefIdr>
      <CreDt>2025-02-17T14:38:22.559677</CreDt>
   </AppHdr>
   <Document>
      <FIToFICstmrCdtTrf>
         <GrpHdr>
            <MsgId>REF-37708</MsgId>
            <CreDtTm>2025-02-17T14:38:22.559678</CreDtTm>
            <NbOfTxs>1</NbOfTxs>
         </GrpHdr>
         <CdtTrfTxInf>
            <IntrBkSttlmAmt Ccy="JPY">48144.00</IntrBkSttlmAmt>
            <Dbtr><Nm>Freeman Ltd</Nm></Dbtr>
            <Cdtr><Nm>Erickson, Blackwell and Ward</Nm></Cdtr>
         </CdtTrfTxInf>
      </FIToFICstmrCdtTrf>
   </Document>
</RequestPayload>