<?xml version="1.0" encoding="UTF-8"?>
<RequestPayload>
   <AppHdr>
      <Fr><FIId><FinInstnId><BICFI>ICBKCNBJXXX</BICFI></FinInstnId></FIId></Fr>
      <To><FIId><FinInstnId><BICFI>BKBKPHMMXXX</BICFI></FinInstnId></FIId></To>
      <BizMsgIdr>REF-65615</BizMsgIdr>
      <MsgDefIdr>pacs.008.001.08</MsgDefIdr>
      <CreDt>2025-02-17T14:38:22.090597</CreDt>
   </AppHdr>
   <Document>
      <FIToFICstmrCdtTrf>
         <GrpHdr>
            <MsgId>REF-65615</MsgId>
            <CreDtTm>2025-02-17T14:38:22.090598</CreDtTm>
            <NbOfTxs>1</NbOfTxs>
         </GrpHdr>
         <CdtTrfTxInf>
            <IntrBkSttlmAmt Ccy="SGD">20483700.00</IntrBkSttlmAmt>
            <Dbtr><Nm>Beasley and Sons</Nm></Dbtr>
            <Cdtr><Nm>Cook-Edwards</Nm></Cdtr>
         </CdtTrfTxInf>
      </FIToFICstmrCdtTrf>
   </Document>
</RequestPayload>