<?xml version="1.0" encoding="UTF-8"?>
<RequestPayload>
   <AppHdr>
      <Fr><FIId><FinInstnId><BICFI>ECOCCIBAXXX</BICFI></FinInstnId></FIId></Fr>
      <To><FIId><FinInstnId><BICFI>AFRIGHACXXX</BICFI></FinInstnId></FIId></To>
      <BizMsgIdr>REF-92352</BizMsgIdr>
      <MsgDefIdr>pacs.008.001.08</MsgDefIdr>
      <CreDt>2025-02-17T14:38:22.684066</CreDt>
   </AppHdr>
   <Document>
      <FIToFICstmrCdtTrf>
         <GrpHdr>
            <MsgId>REF-92352</MsgId>
            <CreDtTm>2025-02-17T14:38:22.684076</CreDtTm>
            <NbOfTxs>1</NbOfTxs>
         </GrpHdr>
         <CdtTrfTxInf>
            <IntrBkSttlmAmt Ccy="USD">41478900.00</IntrBkSttlmAmt>
            <Dbtr><Nm>Nash-Graham</Nm></Dbtr>
            <Cdtr><Nm>Cordova, Warren and Taylor</Nm></Cdtr>
         </CdtTrfTxInf>
      </FIToFICstmrCdtTrf>
   </Document>
</RequestPayload>