<?xml version="1.0" encoding="UTF-8"?>
<RequestPayload>
   <AppHdr>
      <Fr><FIId><FinInstnId><BICFI>STANKEKEXXX</BICFI></FinInstnId></FIId></Fr>
      <To><FIId><FinInstnId><BICFI>SCBLGB2LXXX</BICFI></FinInstnId></FIId></To>
      <BizMsgIdr>REF-39516</BizMsgIdr>
      <MsgDefIdr>pacs.008.001.08</MsgDefIdr>
      <CreDt>2025-02-17T14:38:21.992120</CreDt>
   </AppHdr>
   <Document>
      <FIToFICstmrCdtTrf>
         <GrpHdr>
            <MsgId>REF-39516</MsgId>
            <CreDtTm>2025-02-17T14:38:21.992122</CreDtTm>
            <NbOfTxs>1</NbOfTxs>
         </GrpHdr>
         <CdtTrfTxInf>
            <IntrBkSttlmAmt Ccy="GBP">367117.00</IntrBkSttlmAmt>
            <Dbtr><Nm>Roberts Inc</Nm></Dbtr>
            <Cdtr><Nm>Martin, Castro and Andrews</Nm></Cdtr>
         </CdtTrfTxInf>
      </FIToFICstmrCdtTrf>
   </Document>
</RequestPayload>