<?xml version="1.0" encoding="UTF-8"?>
<RequestPayload>
   <AppHdr>
      <Fr><FIId><FinInstnId><BICFI>CRESCHZZXXX</BICFI></FinInstnId></FIId></Fr>
      <To><FIId><FinInstnId><BICFI>DEUTDEFFXXX</BICFI></FinInstnId></FIId></To>
      <BizMsgIdr>REF-16496</BizMsgIdr>
      <MsgDefIdr>pacs.008.001.08</MsgDefIdr>
      <CreDt>2025-02-17T14:38:21.676669</CreDt>
   </AppHdr>
   <Document>
      <FIToFICstmrCdtTrf>
         <GrpHdr>
            <MsgId>REF-16496</MsgId>
            <CreDtTm>2025-02-17T14:38:21.676671</CreDtTm>
            <NbOfTxs>1</NbOfTxs>
         </GrpHdr>
         <CdtTrfTxInf>
            <IntrBkSttlmAmt Ccy="GBP">4396.90</IntrBkSttlmAmt>
            <Dbtr><Nm>Wilson, Montes and Miller</Nm></Dbtr>
            <Cdtr><Nm>Miller, Adkins and Mahoney</Nm></Cdtr>
         </CdtTrfTxInf>
      </FIToFICstmrCdtTrf>
   </Document>
</RequestPayload>