<?xml version="1.0" encoding="UTF-8"?>
<RequestPayload>
   <AppHdr>
      <Fr><FIId><FinInstnId><BICFI>BNPAFRPPXXX</BICFI></FinInstnId></FIId></Fr>
      <To><FIId><FinInstnId><BICFI>UBSWCHZHXXX</BICFI></FinInstnId></FIId></To>
      <BizMsgIdr>REF-96154</BizMsgIdr>
      <MsgDefIdr>pacs.008.001.08</MsgDefIdr>
      <CreDt>2025-02-17T14:38:21.775012</CreDt>
   </AppHdr>
   <Document>
      <FIToFICstmrCdtTrf>
         <GrpHdr>
            <MsgId>REF-96154</MsgId>
            <CreDtTm>2025-02-17T14:38:21.775014</CreDtTm>
            <NbOfTxs>1</NbOfTxs>
         </GrpHdr>
         <CdtTrfTxInf>
            <IntrBkSttlmAmt Ccy="CHF">3923.50</IntrBkSttlmAmt>
            <Dbtr><Nm>Deleon PLC</Nm></Dbtr>
            <Cdtr><Nm>Santiago PLC</Nm></Cdtr>
         </CdtTrfTxInf>
      </FIToFICstmrCdtTrf>
   </Document>
</RequestPayload>