<?xml version="1.0" encoding="UTF-8"?>
<RequestPayload>
   <AppHdr>
      <Fr><FIId><FinInstnId><BICFI>ECOCGHANXXX</BICFI></FinInstnId></FIId></Fr>
      <To><FIId><FinInstnId><BICFI>ECOCGHANXXX</BICFI></FinInstnId></FIId></To>
      <BizMsgIdr>REF-37337</BizMsgIdr>
      <MsgDefIdr>pacs.008.001.08</MsgDefIdr>
      <CreDt>2025-02-17T14:38:22.798948</CreDt>
   </AppHdr>
   <Document>
      <FIToFICstmrCdtTrf>
         <GrpHdr>
            <MsgId>REF-37337</MsgId>
            <CreDtTm>2025-02-17T14:38:22.798952</CreDtTm>
            <NbOfTxs>1</NbOfTxs>
         </GrpHdr>
         <CdtTrfTxInf>
            <IntrBkSttlmAmt Ccy="CAD">2451600.00</IntrBkSttlmAmt>
            <Dbtr><Nm>Escobar-Johnson</Nm></Dbtr>
            <Cdtr><Nm>Brown, Smith and Davila</Nm></Cdtr>
         </CdtTrfTxInf>
      </FIToFICstmrCdtTrf>
   </Document>
</RequestPayload>