<?xml version="1.0" encoding="UTF-8"?>
<RequestPayload>
   <AppHdr>
      <Fr><FIId><FinInstnId><BICFI>CRESIT2LXXX</BICFI></FinInstnId></FIId></Fr>
      <To><FIId><FinInstnId><BICFI>INGBNL2AXXX</BICFI></FinInstnId></FIId></To>
      <BizMsgIdr>REF-46480</BizMsgIdr>
      <MsgDefIdr>pacs.008.001.08</MsgDefIdr>
      <CreDt>2025-02-17T14:38:22.570745</CreDt>
   </AppHdr>
   <Document>
      <FIToFICstmrCdtTrf>
         <GrpHdr>
            <MsgId>REF-46480</MsgId>
            <CreDtTm>2025-02-17T14:38:22.570746</CreDtTm>
            <NbOfTxs>1</NbOfTxs>
         </GrpHdr>
         <CdtTrfTxInf>
            <IntrBkSttlmAmt Ccy="CHF">1345.20</IntrBkSttlmAmt>
            <Dbtr><Nm>Fitzgerald and Sons</Nm></Dbtr>
            <Cdtr><Nm>Buchanan LLC</Nm></Cdtr>
         </CdtTrfTxInf>
      </FIToFICstmrCdtTrf>
   </Document>
</RequestPayload>