<?xml version="1.0" encoding="UTF-8"?>
<RequestPayload>
   <AppHdr>
      <Fr><FIId><FinInstnId><BICFI>DEUTDEFFXXX</BICFI></FinInstnId></FIId></Fr>
      <To><FIId><FinInstnId><BICFI>BKCHHKHXXXX</BICFI></FinInstnId></FIId></To>
      <BizMsgIdr>REF-36660</BizMsgIdr>
      <MsgDefIdr>pacs.008.001.08</MsgDefIdr>
      <CreDt>2025-02-17T14:38:22.489345</CreDt>
   </AppHdr>
   <Document>
      <FIToFICstmrCdtTrf>
         <GrpHdr>
            <MsgId>REF-36660</MsgId>
            <CreDtTm>2025-02-17T14:38:22.489346</CreDtTm>
            <NbOfTxs>1</NbOfTxs>
         </GrpHdr>
         <CdtTrfTxInf>
            <IntrBkSttlmAmt Ccy="EUR">430536.00</IntrBkSttlmAmt>
            <Dbtr><Nm>Wilson, Jackson and Duncan</Nm></Dbtr>
            <Cdtr><Nm>Stone-Ochoa</Nm></Cdtr>
         </CdtTrfTxInf>
      </FIToFICstmrCdtTrf>
   </Document>
</RequestPayload>