<?xml version="1.0" encoding="UTF-8"?>
<RequestPayload>
   <AppHdr>
      <Fr><FIId><FinInstnId><BICFI>CRESCHZZXXX</BICFI></FinInstnId></FIId></Fr>
      <To><FIId><FinInstnId><BICFI>BNPAFRPPXXX</BICFI></FinInstnId></FIId></To>
      <BizMsgIdr>REF-47015</BizMsgIdr>
      <MsgDefIdr>pacs.008.001.08</MsgDefIdr>
      <CreDt>2025-02-17T14:38:23.057358</CreDt>
   </AppHdr>
   <Document>
      <FIToFICstmrCdtTrf>
         <GrpHdr>
            <MsgId>REF-47015</MsgId>
            <CreDtTm>2025-02-17T14:38:23.057359</CreDtTm>
            <NbOfTxs>1</NbOfTxs>
         </GrpHdr>
         <CdtTrfTxInf>
            <IntrBkSttlmAmt Ccy="EUR">79261.00</IntrBkSttlmAmt>
            <Dbtr><Nm>Robertson, Campos and Lyons</Nm></Dbtr>
            <Cdtr><Nm>Dennis-Brown</Nm></Cdtr>
         </CdtTrfTxInf>
      </FIToFICstmrCdtTrf>
   </Document>
</RequestPayload>