<?xml version="1.0" encoding="UTF-8"?>
<RequestPayload>
   <AppHdr>
      <Fr><FIId><FinInstnId><BICFI>DBSSSGSGXXX</BICFI></FinInstnId></FIId></Fr>
      <To><FIId><FinInstnId><BICFI>ECOCGHANXXX</BICFI></FinInstnId></FIId></To>
      <BizMsgIdr>REF-32307</BizMsgIdr>
      <MsgDefIdr>pacs.008.001.08</MsgDefIdr>
      <CreDt>2025-02-17T14:38:22.067954</CreDt>
   </AppHdr>
   <Document>
      <FIToFICstmrCdtTrf>
         <GrpHdr>
            <MsgId>REF-32307</MsgId>
            <CreDtTm>2025-02-17T14:38:22.067955</CreDtTm>
            <NbOfTxs>1</NbOfTxs>
         </GrpHdr>
         <CdtTrfTxInf>
            <IntrBkSttlmAmt Ccy="SGD">327175.00</IntrBkSttlmAmt>
            <Dbtr><Nm>Smith, Carter and Martin</Nm></Dbtr>
            <Cdtr><Nm>Hernandez Group</Nm></Cdtr>
         </CdtTrfTxInf>
      </FIToFICstmrCdtTrf>
   </Document>
</RequestPayload>